DLD_basic/DLD.py
DLD_basic/Setup.py
DLD_basic/__init__.py
DLD_vig-1.0.0.dist-info/LICENSE
DLD_vig-1.0.0.dist-info/METADATA
DLD_vig-1.0.0.dist-info/WHEEL
DLD_vig-1.0.0.dist-info/top_level.txt
DLD_vig-1.0.0.dist-info/RECORD
