Metadata-Version: 2.1
Name: DLD-vig
Version: 1.0.0
Summary: DLD module
Author-email: Swaroop Nanda <swaroopnanda7@gmail.com>
License: Copyright (c) 2018 The Python Packaging Authority        
Project-URL: Homepage, https://github.com/AssasinThe1/DLD
Classifier: Programming Language :: Python :: 3
Classifier: License :: OSI Approved :: MIT License
Classifier: Operating System :: OS Independent
Requires-Python: >=3.7
License-File: LICENSE
